keble_db/.DS_Store
keble_db/__init__.py
keble_db/crud/__init__.py
keble_db/crud/base.py
keble_db/crud/mongo.py
keble_db/crud/mongo_util.py
keble_db/crud/neo4j.py
keble_db/crud/neo4j_util.py
keble_db/crud/qdrant.py
keble_db/crud/qdrant_util.py
keble_db/crud/sql.py
keble_db/crud/sql_util.py
keble_db/deps/__init__.py
keble_db/deps/api.py
keble_db/mongo.py
keble_db/schemas.py
keble_db/session.py
keble_db/wrapper/__init__.py
keble_db/wrapper/redis.py
keble_db-1.1.2.dist-info/LICENSE
keble_db-1.1.2.dist-info/METADATA
keble_db-1.1.2.dist-info/WHEEL
keble_db-1.1.2.dist-info/RECORD
