Metadata-Version: 2.1
Name: keble-db
Version: 1.1.2
Summary: Keble db
Author: zhenhao-ma
Author-email: bob0103779@gmail.com
Requires-Python: >=3.10,<4.0
Classifier: Programming Language :: Python :: 3
Classifier: Programming Language :: Python :: 3.10
Classifier: Programming Language :: Python :: 3.11
Classifier: Programming Language :: Python :: 3.12
Requires-Dist: deprecated (>=1,<2)
Requires-Dist: greenlet (>=3,<4)
Requires-Dist: keble_helpers (>=1.0.2,<2)
Requires-Dist: motor (>=3,<4)
Requires-Dist: neo4j (>=5,<6)
Requires-Dist: psycopg[binary,pool] (>=3.1.10)
Requires-Dist: pydantic (>=2,<3)
Requires-Dist: pymongo (>=4,<5)
Requires-Dist: qdrant-client (>=1.16.0,<2.0.0)
Requires-Dist: redis (>=5,<6)
Requires-Dist: sqlmodel (>=0,<1)
